excel_tool/All_Module.py
excel_tool/Emblem01.py
excel_tool/EmblemV01.py
excel_tool/FromWorkPC.py
excel_tool/LibPortableV01.py
excel_tool/M01_String.py
excel_tool/__init__.py
excel_tool/learn01.py
excel_tool/other.py
excel_tool/range.py
excel_tool/scratch01.py
excel_tool/test_xlwings02.py
excel_tool/workbook.py
excel_tool/worksheet.py
excel_toolkit/All_Module.py
excel_toolkit/Emblem01.py
excel_toolkit/EmblemV01.py
excel_toolkit/FromWorkPC.py
excel_toolkit/LibPortableV01.py
excel_toolkit/M01_String.py
excel_toolkit/__init__.py
excel_toolkit/cant_use_xt.py
excel_toolkit/fix_bug_xt.py
excel_toolkit/learn01.py
excel_toolkit/other.py
excel_toolkit/range.py
excel_toolkit/scratch01.py
excel_toolkit/test_xlwings02.py
excel_toolkit/workbook.py
excel_toolkit/worksheet.py
excel_toolkit-0.1.3.dist-info/METADATA
excel_toolkit-0.1.3.dist-info/WHEEL
excel_toolkit-0.1.3.dist-info/top_level.txt
excel_toolkit-0.1.3.dist-info/RECORD
